[
  {
    "id": 1,
    "scene": "抽血紧张",
    "patient": "护士姐姐我晕针！能不能不抽啊？",
    "doctor": "咱就跟蚊子叮一下似的，你刷个短视频的功夫就完事儿~ 来，给你个减压球攥着，疼就使劲捏它！",
    "strategy": "生活化类比+分心工具",
    "keywords": ["晕针", "疼痛转移"]
  },
  {
    "id": 2,
    "scene": "住院焦虑",
    "patient": "病房晚上静得吓人，我根本睡不着...",
    "doctor": "我床头给你插个小夜灯咋样？就像家里的小台灯。要不咱下载个白噪音？好多病友都爱听雨声睡觉。",
    "strategy": "环境模拟+共情建议",
    "keywords": ["睡眠障碍", "环境适应"]
  },
  {
    "id": 3,
    "scene": "用药疑惑",
    "patient": "这药片跟糖果似的，真能管用吗？",
    "doctor": "别看它长得萌，里头的成分可是专门治你这个症状的。就像手机充电器，小个头也能蓄满电！",
    "strategy": "视觉联想+功能强调",
    "keywords": ["用药依从性", "药物认知"]
  },
  {
    "id": 4,
    "scene": "检查等待",
    "patient": "都等半小时了，报告咋还没出来？",
    "doctor": "检验科这会儿正给您的样本'拍照'呢，就像咱手机修图得精细调整。我帮您催催，咱先看看这个科普动画？",
    "strategy": "流程拟人化+分心安抚",
    "keywords": ["等待焦虑", "流程解释"]
  },
  {
    "id": 5,
    "scene": "家属急躁",
    "patient": "你们医院效率太低了！",
    "doctor": "叔您消消气，咱这检查就跟煮粥似的，火候不到容易夹生。我给您倒杯茶，顺便说说接下来怎么安排更快。",
    "strategy": "生活比喻+解决方案",
    "keywords": ["家属情绪", "流程优化"]
  },
  {
    "id": 6,
    "scene": "术后疼痛",
    "patient": "刀口火烧火燎的，正常吗？",
    "doctor": "就像新手机刚贴膜有点气泡，伤口愈合也有个过程。咱这个止痛泵就跟手机调亮度似的，疼了就按一下~",
    "strategy": "科技产品类比+操作指导",
    "keywords": ["术后疼痛", "设备使用"]
  },
  {
    "id": 7,
    "scene": "老年抗拒",
    "patient": "我都这把年纪了，还折腾啥手术！",
    "doctor": "王奶奶，咱就当给身体做个大扫除。楼上张阿姨做完现在都能跳广场舞了，回头让她跟您唠唠？",
    "strategy": "生活化比喻+榜样案例",
    "keywords": ["老年治疗", "案例引导"]
  },
  {
    "id": 8,
    "scene": "儿童恐惧",
    "patient": "我不要打针！哇——（大哭）",
    "doctor": "咱们来玩个游戏好不好？你当奥特曼，这个针头是小怪兽，打完针能量就满格啦！打完奖励你小贴纸~",
    "strategy": "角色扮演+即时奖励",
    "keywords": ["儿童医疗", "游戏化沟通"]
  },
  {
    "id": 9,
    "scene": "经济担忧",
    "patient": "这瓶药够我一个月菜钱了！",
    "doctor": "咱医保能报七成，就像超市打折券。我给您调成小包装的，先开两周量试试效果咋样？",
    "strategy": "消费类比+灵活方案",
    "keywords": ["费用压力", "用药调整"]
  },
  {
    "id": 10,
    "scene": "康复疑问",
    "patient": "天天让我抬腿，有啥用啊？",
    "doctor": "这动作就像给膝盖充电，每天充够30次，走路才不卡顿。咱明天试试边看电视边做？",
    "strategy": "电器比喻+习惯绑定",
    "keywords": ["康复训练", "依从性提升"]
  },
  {
    "id": 11,
    "scene": "拆线紧张",
    "patient": "医生轻点儿！线头扯着肉了！",
    "doctor": "咱就像拆快递包装，慢慢揭开不伤内容物~ 您刷会儿朋友圈，我保证五分钟搞定！",
    "strategy": "生活场景类比+注意力转移",
    "keywords": ["术后护理", "疼痛管理"]
  },
  {
    "id": 12,
    "scene": "糖尿病饮食",
    "patient": "红烧肉一口都不能吃？太残忍了吧！",
    "doctor": "咱把大块肉换成薄片，就像手机开省电模式。每月奖励自己两次，每次不超过三块咋样？",
    "strategy": "折中方案+量化控制",
    "keywords": ["饮食管理", "慢性病"]
  },
  {
    "id": 13,
    "scene": "放射检查",
    "patient": "这机器看着像科幻片，不会变异吧？",
    "doctor": "这就是个大号相机，咔嚓一下给内脏拍写真。检查完咱看片子就像选照片，找出最好那张！",
    "strategy": "科技祛魅+可视化解释",
    "keywords": ["影像检查", "设备恐惧"]
  },
  {
    "id": 14,
    "scene": "便秘困扰",
    "patient": "三天没上厕所了，肚子像揣个铅球！",
    "doctor": "咱给肠道做个广播体操——顺时针揉腹50下，喝完这杯温水立马试试，好多病友说特管用！",
    "strategy": "动作指导+病友见证",
    "keywords": ["消化道症状", "非药物疗法"]
  },
  {
    "id": 15,
    "scene": "老年健忘",
    "patient": "药片总忘记吃，儿子老骂我！",
    "doctor": "咱把药盒和遥控器放一起，每晚追剧前就像换台一样吃药。我给您写个荧光贴纸提醒咋样？",
    "strategy": "习惯绑定+视觉提示",
    "keywords": ["用药管理", "老年照护"]
  },
  {
    "id": 16,
    "scene": "孕检焦虑",
    "patient": "胎动少了是不是出问题了？",
    "doctor": "宝宝就像手机开了静音模式，咱用胎心仪'打电话'听听？这是今早其他宝妈的数据，都在正常范围呢~",
    "strategy": "科技类比+数据对比",
    "keywords": ["孕期焦虑", "胎动监测"]
  },
  {
    "id": 17,
    "scene": "针灸恐惧",
    "patient": "针扎进去会不会断在肉里啊？",
    "doctor": "这针比头发丝还细，扎上就像蚊子腿轻碰下。您玩会儿消消乐，结束还能数数扎了几个'小蚂蚁'~",
    "strategy": "视觉类比+游戏化转移",
    "keywords": ["中医治疗", "侵入性操作"]
  },
  {
    "id": 18,
    "scene": "复查拖延",
    "patient": "最近太忙了，复查晚点行不行？",
    "doctor": "身体就像爱车，到公里数得保养。咱约个周末加班门诊，我给您留个VIP'工位'咋样？",
    "strategy": "机械保养类比+便利提供",
    "keywords": ["健康管理", "依从性"]
  },
  {
    "id": 19,
    "scene": "过敏反应",
    "patient": "全身起红包，痒得想撞墙！",
    "doctor": "咱先来个冰镇面膜疗法，把药膏放冰箱冰会儿再涂。边涂边数红包，超过20个奖励冰淇淋~",
    "strategy": "感官缓解+计数游戏",
    "keywords": ["皮肤症状", "瘙痒管理"]
  },
  {
    "id": 20,
    "scene": "戒烟劝导",
    "patient": "抽了三十年哪戒得掉！",
    "doctor": "咱先从'减焦油版本'开始，就像手机从4G切5G。每周记录抽烟钱，月底够给孙子买乐高了！",
    "strategy": "渐进替代+可视化激励",
    "keywords": ["成瘾行为", "习惯改变"]
  },
  {
    "id": 21,
    "scene": "儿童喂药",
    "patient": "苦死了！呸！（吐药）",
    "doctor": "奥特曼专用能量水来咯~ 喝完立马解锁喷射技能！快看药瓶上的恐龙贴纸在给你加油呢！",
    "strategy": "角色扮演+视觉激励",
    "keywords": ["儿科用药", "喂药技巧"]
  },
  {
    "id": 22,
    "scene": "放疗脱发",
    "patient": "头发掉成蒲公英了，怎么见人...",
    "doctor": "咱挑顶星空图案的潮款假发，就像天天换发型！病房李阿姨戴的那款，她女婿都认不出来呢~",
    "strategy": "时尚重塑+案例引导",
    "keywords": ["形象焦虑", "肿瘤治疗"]
  },
  {
    "id": 23,
    "scene": "胃镜抗拒",
    "patient": "管子插喉咙？杀了我算了！",
    "doctor": "现在有无痛模式，就像坐云霄飞车前喝杯'安睡奶茶'。醒过来就能拿'勇敢者证书'，朋友圈点赞收割机~",
    "strategy": "恐惧转化+社交激励",
    "keywords": ["内镜检查", "侵入性操作"]
  },
  {
    "id": 24,
    "scene": "长期输液",
    "patient": "手背都扎成筛子了！",
    "doctor": "咱给血管来个'轮休制'，今天扎左手明天换右手。贴上卡通创可贴，就像获得战斗勋章！",
    "strategy": "轮换策略+成就可视化",
    "keywords": ["静脉治疗", "穿刺管理"]
  },
  {
    "id": 25,
    "scene": "义齿不适",
    "patient": "假牙硌得疼，还不如不用！",
    "医生": "新鞋还得磨两天呢，咱先每天戴两小时逐步适应。记得用这个'义齿按摩膏'，就像给牙龈做SPA~",
    "strategy": "生活类比+渐进适应",
    "keywords": ["修复治疗", "异物感适应"]
  },
  {
    "id": 26,
    "scene": "哮喘发作",
    "patient": "喘得...像破风箱...救命！",
    "doctor": "慢慢来，像吸珍珠奶茶那样用吸管呼吸。这个喷雾剂就像119灭火器，按一下火速救援！",
    "strategy": "具象化指导+设备拟人化",
    "keywords": ["急性发作", "呼吸训练"]
  },
  {
    "id": 27,
    "scene": "产后抑郁",
    "patient": "宝宝一哭我就想跳楼...",
    "doctor": "新生儿就像没装操作系统的手机，咱正在互相适配呢。每天给自己一小时'飞行模式'，月嫂阿姨随时待命！",
    "strategy": "科技类比+喘息时间",
    "keywords": ["产后心理", "母婴照护"]
  },
  {
    "id": 28,
    "scene": "康复懈怠",
    "patient": "走路练习太枯燥了！",
    "doctor": "咱把走廊当T台，每走十步换个造型。小护士们当评委打分，满100分解锁水果拼盘~",
    "strategy": "游戏化训练+即时奖励",
    "keywords": ["康复治疗", "动机维持"]
  },
  {
    "id": 29,
    "scene": "化疗呕吐",
    "patient": "吐得胆汁都出来了...",
    "doctor": "咱试试'冰冻柠檬疗法'，含片柠檬冰再打药。就像给胃装个空调，这是病友群投票top1妙招！",
    "strategy": "症状缓解妙招+群体智慧",
    "keywords": ["化疗反应", "恶心控制"]
  },
  {
    "id": 30,
    "scene": "临终关怀",
    "patient": "疼得受不了，让我走吧...",
    "doctor": "咱们把止痛泵调到'温泉模式'，就像泡在暖洋洋的水里。要不要听听孙子录的睡前故事？",
    "strategy": "感官重构+情感连接",
    "keywords": ["疼痛控制", "临终关怀"]
  },
  {
    "id": 31,
    "scene": "拆线恐惧",
    "patient": "医生你慢点！我听见剪刀声腿都软了！",
    "doctor": "咱就当修剪死皮，我用的可是美容级小剪刀~ 您刷刷电商APP，看到喜欢的我帮您加购！",
    "strategy": "注意力转移+消费激励",
    "keywords": ["术后护理","工具美化"]
  },
  {
    "id": 32,
    "scene": "胰岛素注射",
    "patient": "天天扎肚子，我都成筛子了！",
    "doctor": "咱给肚皮划个'战区图'，每天换个区域就像手机换壁纸。试试这个隐形针头，比睫毛还细呢！",
    "strategy": "区域轮换+工具升级",
    "keywords": ["糖尿病","注射管理"]
  },
  {
    "id": 33,
    "scene": "儿童拍片",
    "patient": "那个大机器会吃人！我不要进去！！",
    "doctor": "这是太空舱体验器，躺进去就能检测超能力！看，操作台有奥特曼按钮，你妈妈可以远程启动~",
    "strategy": "幻想情境+亲子互动",
    "keywords": ["儿科检查","设备恐惧"]
  },
  {
    "id": 34,
    "scene": "痔疮尴尬",
    "patient": "这地方怎么好意思给人看...",
    "doctor": "我们每天看pp就像程序员看代码，只关注'bug'位置。给您个隐私保护按钮，检查时随时暂停~",
    "strategy": "职业类比+控制感赋予",
    "keywords": ["隐私部位","尴尬缓解"]
  },
  {
    "id": 35,
    "scene": "透析焦虑",
    "patient": "机器一响我就心慌，像在鬼门关走钢丝！",
    "doctor": "透析机是您的'人工肾保姆'，报警声就像外卖提示音。咱们边治疗边追剧，最新《甄嬛传》续集要上了~",
    "strategy": "设备拟人化+娱乐分心",
    "keywords": ["血液净化","设备适应"]
  },
  {
    "id": 36,
    "scene": "癫痫发作",
    "patient": "发病时流口水太丢人了...",
    "doctor": "大脑就像突然死机的电脑，重启时漏点电很正常。给您定制时尚款口水巾，病友群都在团购呢！",
    "strategy": "科技类比+形象管理",
    "keywords": ["神经系统","病耻感"]
  },
  {
    "id": 37,
    "scene": "孕吐严重",
    "patient": "吐得黄疸水都出来了，孩子能受得了吗？",
    "doctor": "宝宝现在像住在防震帐篷里，您吃颗薄荷糖就像给他装空调。这是其他准妈妈的止吐妙招TOP5~",
    "strategy": "胎儿保护可视化+群体智慧",
    "keywords": ["妊娠反应","营养管理"]
  },
  {
    "id": 38,
    "scene": "义眼安装",
    "patient": "装个假眼珠晚上会不会自己掉出来？",
    "doctor": "我们的义眼像定制美瞳，有磁吸装置比耳环还牢。张先生装了还能玩VR游戏，这是他滑雪的视频~",
    "strategy": "技术解释+案例证明",
    "keywords": ["假体适应","功能展示"]
  },
  {
    "id": 39,
    "scene": "狂犬疫苗",
    "patient": "打这么多针，我会不会变异啊？",
    "doctor": "疫苗就像给免疫系统发通缉令，打完您就是病毒绝缘体！最后一针送漫威联名创可贴，集齐有礼~",
    "strategy": "免疫教育+收集激励",
    "keywords": ["疫苗接种","恐惧缓解"]
  },
  {
    "id": 40,
    "scene": "体检尴尬",
    "patient": "身高体重还要当众测？太社死了！",
    "doctor": "我们新装了体测盲盒机，投币出结果就像抓娃娃。数据直接加密传到手机，绝对隐私保护~",
    "strategy": "游戏化流程+技术保障",
    "keywords": ["体检流程","隐私焦虑"]
  },
  {
    "id": 41,
    "scene": "化疗脱发",
    "patient": "头皮痒得像蚂蚁在搬家！",
    "doctor": "试试这个冰感喷雾，就像给头皮吃冰激凌。晚上咱戴丝绸睡帽，比裸睡还舒服~",
    "strategy": "感官舒缓+舒适体验",
    "keywords": ["肿瘤护理","症状缓解"]
  },
  {
    "id": 42,
    "scene": "胃管抵触",
    "patient": "鼻子插管太难受了，拔了吧！",
    "doctor": "胃管就像给您装了个营养外卖通道，咱们调个舒服姿势，像吸珍珠奶茶那样慢慢适应~",
    "strategy": "功能类比+渐进适应",
    "keywords": ["侵入性治疗","舒适护理"]
  },
  {
    "id": 43,
    "scene": "临终焦虑",
    "patient": "咽气时会不会很丑？",
    "doctor": "我们会像修图师那样帮您保持安详面容，给您准备最爱的香水味，就像睡着做个美梦~",
    "strategy": "形象维护+感官安抚",
    "keywords": ["临终关怀","死亡教育"]
  },
  {
    "id": 44,
    "scene": "康复枯燥",
    "patient": "天天抬腿一百次，机器人也腻了！",
    "doctor": "咱们把动作编成K-pop舞蹈，手机录视频上传能积赞换理疗次数！昨天李阿姨视频点击过千呢~",
    "strategy": "娱乐化改编+社交激励",
    "keywords": ["康复训练","动机维持"]
  },
  {
    "id": 45,
    "scene": "造口护理",
    "patient": "粪袋漏了怎么办？太丢人了！",
    "doctor": "造口就像身体开的VIP通道，咱们用防漏贴就像手机贴膜。病友老陈戴着它跑完马拉松啦！",
    "strategy": "功能重构+榜样力量",
    "keywords": ["肠造口","生活适应"]
  },
  {
    "id": 46,
    "scene": "吸氧抗拒",
    "patient": "插着鼻管像匹诺曹！",
    "doctor": "这是氧气美颜仪，明星红毯前都偷偷用~ 咱们选个水晶蓝款，拍侧颜照绝对出圈！",
    "strategy": "形象美化+时尚设计",
    "keywords": ["氧疗护理","形象焦虑"]
  },
  {
    "id": 47,
    "scene": "放疗定位",
    "patient": "纹身标记洗不掉怎么办？",
    "doctor": "这是银河系最小文身，像颗小星星。等治疗结束，咱可以添加星座图案变成潮款~",
    "strategy": "标记美化+未来规划",
    "keywords": ["放疗护理","皮肤标记"]
  },
  {
    "id": 48,
    "scene": "留置针恐惧",
    "patient": "针头老晃悠，血管要戳破了！",
    "doctor": "咱们给针头穿'固定袜'，贴上卡通贴就像戴发卡。手机支架已备好，追剧时它绝对乖乖的~",
    "strategy": "儿童化处理+娱乐配套",
    "keywords": ["静脉治疗","设备固定"]
  },
  {
    "id": 49,
    "scene": "认知障碍",
    "patient": "你们是不是在骗我住院？",
    "doctor": "咱们这是记忆训练营，每天玩拼图赚积分，攒够分换孙子合照台历~ 您看张大爷做的多棒！",
    "strategy": "游戏化叙事+亲情激励",
    "keywords": ["老年痴呆","住院适应"]
  },
  {
    "id": 50,
    "scene": "家属冲突",
    "patient": "儿子女儿为我的治疗费吵翻了！",
    "doctor": "咱就当开家庭会议，我当主持人用医疗账单生成器做个PPT，像分家务那样分配治疗任务~",
    "strategy": "技术工具+责任具象化",
    "keywords": ["家庭矛盾","费用沟通"]
  }
]